{
  "id": "NFR-INT-012",
  "epicId": "integration-interoperability",
  "requirementType": "non-functional",
  "title": "CommonWell Health Alliance membership",
  "summary": "HIE Participation: CommonWell Health Alliance membership",
  "description": "Maintain CommonWell Health Alliance membership to support interoperability and enable seamless health information exchange across the CommonWell network.",
  "acceptanceCriteria": [],
  "status": "todo",
  "priority": "medium",
  "manager": "person-001",
  "createdAt": "2025-12-10T11:47:35.357Z",
  "updatedAt": "2025-12-10T11:47:35.357Z",
  "plannedStartDate": null,
  "plannedDueDate": null,
  "actualStartDate": null,
  "actualDueDate": null,
  "dueDate": null,
  "tags": [
    "non-functional",
    "INT",
    "HIE Participation"
  ],
  "estimate": {
    "storyPoints": 0,
    "confidence": "medium"
  },
  "relatedStories": [],
  "mentions": [],
  "files": [],
  "metadata": {
    "createdBy": "system",
    "lastEditedBy": "system",
    "custom": {}
  },
  "deleted": false,
  "archived": false
}
