{
  "id": "F-SCHED-012",
  "requirementType": "functional",
  "epicId": "intelligent-scheduling",
  "title": "Same-day appointment prevention (2-hour buffer)",
  "summary": "Prevent patients from booking same-day appointments with a 2-hour minimum buffer.",
  "description": "Implement a business rule that prevents patients from booking appointments on the same day, requiring at least a 2-hour buffer. This ensures adequate preparation time and reduces last-minute scheduling conflicts.",
  "acceptanceCriteria": [],
  "status": "todo",
  "priority": "medium",
  "manager": "person-001",
  "createdAt": "2025-01-15T00:00:00Z",
  "updatedAt": "2025-01-15T00:00:00Z",
  "dueDate": null,
  "tags": [
    "functional",
    "SCHED",
    "Patient Self-Scheduling"
  ],
  "estimate": {
    "storyPoints": 0,
    "confidence": "medium"
  },
  "relatedStories": [],
  "mentions": [],
  "files": [],
  "metadata": {
    "createdBy": "system",
    "lastEditedBy": "system",
    "custom": {}
  },
  "deleted": false,
  "archived": false
}

